kTemplate/__init__.py
kTemplate/elements.py
kTemplate/gen_elements.py
kTemplate/tag.py
ktemplate-0.5.1.dist-info/LICENSE
ktemplate-0.5.1.dist-info/METADATA
ktemplate-0.5.1.dist-info/WHEEL
ktemplate-0.5.1.dist-info/RECORD
