Metadata-Version: 2.1
Name: kTemplate
Version: 0.5.1
Summary: pythonic way to create HTML/XML/SVG
Home-page: https://hoishing.github.io/kTemplate
License: MIT
Keywords: template,html
Author: Kelvin Ng
Author-email: hoishing@gmail.com
Requires-Python: >=3.12,<4.0
Classifier: Development Status :: 4 - Beta
Classifier: Intended Audience :: Developers
Classifier: License :: OSI Approved :: MIT License
Classifier: Programming Language :: Python :: 3
Classifier: Programming Language :: Python :: 3.12
Classifier: Topic :: Internet :: WWW/HTTP :: Dynamic Content
Project-URL: Documentation, https://hoishing.github.io/kTemplate
Project-URL: Repository, https://github.com/hoishing/kTemplate
